[
  {
    "chunk_id": "GBZ21_2006_scope_001",
    "file_name": "19.GBZ 21-2006职业性光接触性皮炎诊断标准.pdf",
    "source": "GBZ 21-2006 职业性光接触性皮炎诊断标准",
    "source_type": "national_occupational_diagnostic_standard",
    "year": 2006,
    "type": "standard_rule",
    "chunk_level": "scope",
    "parent_section": "1 范围",
    "title": "标准范围与适用对象",
    "disease_name": "职业性光接触性皮炎",
    "hazard": "光敏物+日光(紫外线)",
    "system_target": "皮肤",
    "text": "本标准规定了职业性光接触性皮炎的诊断及处理原则，适用于职业性光接触性皮炎的诊断及处理，非职业性光接触性皮炎亦可参照使用。",
    "retrieval_hint": "当输入涉及光敏物接触后日晒发病、光毒性或光变应性皮炎时优先召回。",
    "priority": "high",
    "status": "manual_checked_from_uploaded_pdf"
  },
  {
    "chunk_id": "GBZ21_2006_principle_001",
    "file_name": "19.GBZ 21-2006职业性光接触性皮炎诊断标准.pdf",
    "source": "GBZ 21-2006 职业性光接触性皮炎诊断标准",
    "source_type": "national_occupational_diagnostic_standard",
    "year": 2006,
    "type": "standard_rule",
    "chunk_level": "diagnostic_principle",
    "parent_section": "2 诊断原则",
    "title": "诊断原则",
    "disease_name": "职业性光接触性皮炎",
    "hazard": "光敏物+日光(紫外线)",
    "system_target": "皮肤",
    "text": "根据明确的职业接触史、发病前日光（紫外线）照射史与临床表现，参考现场职业卫生学调查和同工种发病情况，必要时结合皮肤光斑贴试验综合分析，并排除其他非职业性因素引起的类似皮肤病后方可诊断。",
    "retrieval_hint": "用于构造光接触性皮炎诊断证据链。",
    "priority": "high",
    "status": "manual_checked_from_uploaded_pdf"
  },
  {
    "chunk_id": "GBZ21_2006_phototoxic_001",
    "file_name": "19.GBZ 21-2006职业性光接触性皮炎诊断标准.pdf",
    "source": "GBZ 21-2006 职业性光接触性皮炎诊断标准",
    "source_type": "national_occupational_diagnostic_standard",
    "year": 2006,
    "type": "standard_rule",
    "chunk_level": "diagnostic_type",
    "parent_section": "3.1 职业性光毒性接触性皮炎",
    "title": "职业性光毒性接触性皮炎诊断标准",
    "disease_name": "职业性光接触性皮炎",
    "hazard": "光敏物+紫外线",
    "system_target": "皮肤",
    "text": "皮损呈局限性片状红斑，有烧灼感或疼痛，严重时可出现水肿和水疱，常伴结膜炎及全身症状；接触光敏物并受日光照射后即刻发病，多发生于曝光部位，同工种同条件下多数人发病；脱离接触或避免日光后炎症消退较快，局部常留有不同程度色素沉着。",
    "retrieval_hint": "适用于光毒性损伤判别。",
    "priority": "high",
    "status": "manual_checked_from_uploaded_pdf"
  },
  {
    "chunk_id": "GBZ21_2006_photoallergic_001",
    "file_name": "19.GBZ 21-2006职业性光接触性皮炎诊断标准.pdf",
    "source": "GBZ 21-2006 职业性光接触性皮炎诊断标准",
    "source_type": "national_occupational_diagnostic_standard",
    "year": 2006,
    "type": "standard_rule",
    "chunk_level": "diagnostic_type",
    "parent_section": "3.2 职业性光变应性接触性皮炎",
    "title": "职业性光变应性接触性皮炎诊断标准",
    "disease_name": "职业性光接触性皮炎",
    "hazard": "光敏物+紫外线",
    "system_target": "皮肤",
    "text": "皮损为水肿性红斑，上有小丘疹或水疱，边缘常不清楚，伴不同程度瘙痒；初次接触致敏约需5至14天或更久，致敏后再接触常可在24小时内发病；皮损初发于接触部位，可扩展至全身；同工种同条件下仅少数人发病；脱离接触后常遗留不同程度色素沉着；皮肤光斑贴试验结果常为阳性。",
    "retrieval_hint": "适用于光变应性接触性皮炎和光斑贴试验阳性场景。",
    "priority": "high",
    "status": "manual_checked_from_uploaded_pdf"
  },
  {
    "chunk_id": "GBZ21_2006_disposition_001",
    "file_name": "19.GBZ 21-2006职业性光接触性皮炎诊断标准.pdf",
    "source": "GBZ 21-2006 职业性光接触性皮炎诊断标准",
    "source_type": "national_occupational_diagnostic_standard",
    "year": 2006,
    "type": "standard_rule",
    "chunk_level": "processing_action",
    "parent_section": "4 处理原则",
    "title": "处理原则",
    "disease_name": "职业性光接触性皮炎",
    "hazard": "光敏物+日光(紫外线)",
    "system_target": "治疗/岗位处理",
    "text": "应及时清除皮肤上残留的光敏物，避免接触光敏物及日光（紫外线）照射，并根据病情按接触性皮炎治疗原则对症治疗。严重光毒性皮炎治疗期间可适当休息；严重且反复发作的光变应性接触性皮炎可调换工种并避免接触光敏物。",
    "retrieval_hint": "用于生成清洗、避光、休息、调岗建议。",
    "priority": "high",
    "status": "manual_checked_from_uploaded_pdf",
    "processing_action": "清除光敏物/避光/对症治疗/必要时调岗"
  },
  {
    "chunk_id": "GBZ21_2006_photopatch_001",
    "file_name": "19.GBZ 21-2006职业性光接触性皮炎诊断标准.pdf",
    "source": "GBZ 21-2006 职业性光接触性皮炎诊断标准",
    "source_type": "national_occupational_diagnostic_standard",
    "year": 2006,
    "type": "appendix_test_method",
    "chunk_level": "test_method",
    "parent_section": "附录A",
    "title": "皮肤光斑贴试验方法",
    "disease_name": "职业性光接触性皮炎",
    "hazard": "光敏物+日光(紫外线)",
    "system_target": "皮肤试验",
    "text": "附录A给出了皮肤光斑贴试验的适用范围、试验材料、照射方法、反应程度判定及常见职业性光变应原浓度，可用于辅助诊断职业性光变应性接触性皮炎。",
    "retrieval_hint": "当需要光斑贴试验方法、判读或常见光变应原时召回。",
    "priority": "medium",
    "status": "manual_checked_from_uploaded_pdf"
  }
]